VPi/GPIO.py
VPi/__init__.py
VPi/adafruit_mcp4725.py
VPi/adafruit_tca9548a.py
VPi/board.py
VPi/busio.py
VPi/spidev.py
raspberrypi/__init__.py
raspberrypi/pin.py
raspberrypi/raspi_1b_rev1.py
raspberrypi/raspi_1b_rev2.py
raspberrypi/raspi_40pin.py
raspberrypi/raspi_cm.py
VPi-0.1.4.dist-info/LICENSE
VPi-0.1.4.dist-info/METADATA
VPi-0.1.4.dist-info/WHEEL
VPi-0.1.4.dist-info/top_level.txt
VPi-0.1.4.dist-info/RECORD
