Metadata-Version: 2.1
Name: VPi
Version: 0.1.4
Summary: Virtual Pi Library for Raspberry Pi
Home-page: https://github.com/codenio/
Author: Aananth K
Author-email: aananthraj1995@gmail.com
License: GPL-3.0
Platform: UNKNOWN
Requires-Dist: numpy (==1.19.5)
